O2DESPy/__init__.py
O2DESPy/assets.py
O2DESPy/event.py
O2DESPy/hour_counter.py
O2DESPy/main.py
O2DESPy/phase_tracker.py
O2DESPy/pointer.py
O2DESPy/sandbox.py
O2DESPy/application/__init__.py
O2DESPy/application/config.py
O2DESPy/demos/__init__.py
O2DESPy/log/__init__.py
O2DESPy/log/logger.py
qwertywerty-1.0.0.dist-info/LICENSE
qwertywerty-1.0.0.dist-info/METADATA
qwertywerty-1.0.0.dist-info/WHEEL
qwertywerty-1.0.0.dist-info/top_level.txt
qwertywerty-1.0.0.dist-info/RECORD
